MANIFEST.in
README.md
setup.cfg
setup.py
collective/__init__.py
collective.listjs.egg-info/PKG-INFO
collective.listjs.egg-info/SOURCES.txt
collective.listjs.egg-info/dependency_links.txt
collective.listjs.egg-info/entry_points.txt
collective.listjs.egg-info/namespace_packages.txt
collective.listjs.egg-info/not-zip-safe
collective.listjs.egg-info/paster_plugins.txt
collective.listjs.egg-info/requires.txt
collective.listjs.egg-info/top_level.txt
collective/listjs/__init__.py
collective/listjs/configure.zcml
collective/listjs/browser/__init__.py
collective/listjs/browser/configure.zcml
collective/listjs/browser/folderviews.py
collective/listjs/browser/ecmascripts/list.js
collective/listjs/browser/ecmascripts/list.min.js
collective/listjs/browser/stylesheets/list.js.css
collective/listjs/browser/templates/folder_simple_view.pt
collective/listjs/browser/templates/folder_tabular_view.pt
collective/listjs/locales/collective.listjs.pot
collective/listjs/locales/it/LC_MESSAGES/collective.listjs-it.po
collective/listjs/profiles/default/cssregistry.xml
collective/listjs/profiles/default/jsregistry.xml
collective/listjs/profiles/default/metadata.xml
collective/listjs/tests/__init__.py
collective/listjs/tests/base.py
collective/listjs/tests/test_integration_unit.py
docs/HISTORY.txt
docs/INSTALL.txt
docs/LICENSE.GPL
docs/LICENSE.txt