Metadata-Version: 1.0
Name: collective.listjs
Version: 0.1.2
Summary: Plone integration for Listjs (http://www.listjs.com)
Home-page: http://svn.plone.org/svn/collective/
Author: zedr
Author-email: zedr@ipnext.it
License: GPL
Keywords: listjs
Platform: UNKNOWN
Classifier: Framework :: Plone
Classifier: Programming Language :: Python
